MANIFEST.in
README.txt
plonetheme.gov-configure.zcml
setup.cfg
setup.py
docs/HISTORY.txt
docs/INSTALL.txt
docs/LICENSE.GPL
docs/LICENSE.txt
plonetheme/__init__.py
plonetheme.gov.egg-info/PKG-INFO
plonetheme.gov.egg-info/SOURCES.txt
plonetheme.gov.egg-info/dependency_links.txt
plonetheme.gov.egg-info/entry_points.txt
plonetheme.gov.egg-info/namespace_packages.txt
plonetheme.gov.egg-info/not-zip-safe
plonetheme.gov.egg-info/paster_plugins.txt
plonetheme.gov.egg-info/requires.txt
plonetheme.gov.egg-info/top_level.txt
plonetheme/gov/.DS_Store
plonetheme/gov/__init__.py
plonetheme/gov/configure.zcml
plonetheme/gov/events.py
plonetheme/gov/profiles.zcml
plonetheme/gov/setuphandlers.py
plonetheme/gov/skins.zcml
plonetheme/gov/tests.py
plonetheme/gov/version.txt
plonetheme/gov/browser/__init__.py
plonetheme/gov/browser/carousel.pt
plonetheme/gov/browser/carousel_item_tile.pt
plonetheme/gov/browser/composer.py
plonetheme/gov/browser/configure.zcml
plonetheme/gov/browser/file_view.pt
plonetheme/gov/browser/file_view.py
plonetheme/gov/browser/global_social.pt
plonetheme/gov/browser/gov_folder_view.pt
plonetheme/gov/browser/gov_folder_view.py
plonetheme/gov/browser/interfaces.py
plonetheme/gov/browser/newsletter-html.pt
plonetheme/gov/browser/newsletter-ikpob-html.pt
plonetheme/gov/browser/relateditems.pt
plonetheme/gov/browser/searchview.py
plonetheme/gov/browser/viewlet.pt
plonetheme/gov/browser/viewlets.py
plonetheme/gov/browser/images/README.txt
plonetheme/gov/browser/images/backgroundTexture.jpg
plonetheme/gov/browser/images/backgroundTextureGray.jpg
plonetheme/gov/browser/images/linkedin.png
plonetheme/gov/browser/images/rss.png
plonetheme/gov/browser/images/searchbutton.jpg
plonetheme/gov/browser/images/share.png
plonetheme/gov/browser/images/twitter.png
plonetheme/gov/browser/stylesheets/README.txt
plonetheme/gov/browser/stylesheets/carousel.css
plonetheme/gov/browser/stylesheets/footer.css
plonetheme/gov/browser/stylesheets/menu.css
plonetheme/gov/browser/stylesheets/searchresults.css
plonetheme/gov/browser/templates/search.pt
plonetheme/gov/locales/README.txt
plonetheme/gov/profiles/default/cssregistry.xml
plonetheme/gov/profiles/default/jsregistry.xml
plonetheme/gov/profiles/default/metadata.xml
plonetheme/gov/profiles/default/plonetheme.gov_various.txt
plonetheme/gov/profiles/default/skins.xml
